spotube/__init__.py
spotube/authenticator.py
spotube/dependency_handler.py
spotube/download_manager.py
spotube/downloader_utils.py
spotube/progress_bar.py
spotube-0.5.29.dist-info/LICENSE
spotube-0.5.29.dist-info/METADATA
spotube-0.5.29.dist-info/WHEEL
spotube-0.5.29.dist-info/RECORD
