Metadata-Version: 2.1
Name: spotube
Version: 0.5.29
Summary: A Python package to download Spotify playlists locally including the cover art, metadata and lyrics by leveraging the Spotify, YouTube and Genius APIs.
Home-page: https://github.com/GiorgosNik/spotube-package
License: Free for non-commercial use
Author: GiorgosNik
Author-email: giorgosnl17@gmail.com
Requires-Python: >=3.10,<4.0
Classifier: License :: Other/Proprietary License
Classifier: Programming Language :: Python :: 3
Classifier: Programming Language :: Python :: 3.10
Classifier: Programming Language :: Python :: 3.11
Requires-Dist: eyed3 (>=0.9.7,<0.10.0)
Requires-Dist: lyricsgenius (>=3.0.1,<4.0.0)
Requires-Dist: pydub (>=0.25.1,<0.26.0)
Requires-Dist: pytest (>=7.2.2,<8.0.0)
Requires-Dist: requests (>=2.28.2,<3.0.0)
Requires-Dist: spotipy (>=2.22.1,<3.0.0)
Requires-Dist: tqdm (>=4.65.0,<5.0.0)
Requires-Dist: youtube-search-python (>=1.6.6,<2.0.0)
Requires-Dist: yt-dlp (>=2025.3.21,<2026.0.0)
Project-URL: Repository, https://github.com/GiorgosNik/spotube-package
